data_logger_api_sdk/__init__.py
data_logger_api_sdk/data_logger_api_sdk.py
data_logger_api_sdk/data_logger_sdk_config.py
data_logger_api_sdk/py.typed
data_logger_api_sdk/types/__init__.py
data_logger_api_sdk/types/api_bs_traffic_stats.py
data_logger_api_sdk/types/api_device_data_history.py
data_logger_api_sdk/types/api_last_bs_data_by_device_macs.py
data_logger_api_sdk/types/api_packet_types.py
data_logger_api_sdk/types/api_protocol_types.py
ul_data_logger_api_sdk-2.0.6.dist-info/METADATA
ul_data_logger_api_sdk-2.0.6.dist-info/WHEEL
ul_data_logger_api_sdk-2.0.6.dist-info/top_level.txt
ul_data_logger_api_sdk-2.0.6.dist-info/RECORD
