Metadata-Version: 2.1
Name: ul-data-logger-api-sdk
Version: 2.0.6
Summary: Data logger API sdk
Author: Unic-lab
License: MIT
Platform: any
Classifier: Intended Audience :: Developers
Classifier: License :: OSI Approved :: MIT License
Classifier: Programming Language :: Python
Classifier: Programming Language :: Python :: 3.6
Classifier: Programming Language :: Python :: 3.7
Classifier: Programming Language :: Python :: 3.8
Classifier: Programming Language :: Python :: 3.9
Classifier: Operating System :: OS Independent
Requires-Dist: ul-unipipeline (>=2.0.0)
Requires-Dist: tqdm (==4.66.1)
